wefact/__init__.py
wefact/config.py
wefact/exceptions.py
wefact/request.py
wefact/utils.py
wefact/version.py
wefact/wefact.py
wefact/enums/__init__.py
wefact/enums/actions.py
wefact/enums/cost_category_actions.py
wefact/enums/credit_invoice_actions.py
wefact/enums/debtor_actions.py
wefact/enums/interaction_actions.py
wefact/enums/invoice_actions.py
wefact/enums/quote_actions.py
wefact/enums/subscription_actions.py
wefact/enums/task_actions.py
wefact/enums/transaction_actions.py
wefact/enums/variables.py
wefact/resources/__init__.py
wefact/resources/base.py
wefact/resources/cost_category.py
wefact/resources/credit_invoice.py
wefact/resources/creditor.py
wefact/resources/debtor.py
wefact/resources/group.py
wefact/resources/interaction.py
wefact/resources/invoice.py
wefact/resources/product.py
wefact/resources/quote.py
wefact/resources/settings.py
wefact/resources/subscription.py
wefact/resources/task.py
wefact/resources/transaction.py
wefact_cli/__init__.py
wefact_cli/__main__.py
wefact_cli/cli.py
wefact_cli/config.py
wefact_cli/dummy_data.py
wefact_cli/test_runner.py
wefact_cli/endpoints/__init__.py
wefact_cli/endpoints/base_tester.py
wefact_cli/endpoints/interactive_tester.py
wefact_cli/endpoints/invoice_tester.py
wefact_cli/ui/__init__.py
wefact_cli/ui/panels.py
wefact_cli/ui/prompts.py
wefact_cli/ui/tables.py
wefact_cli/utils/__init__.py
wefact_cli/utils/data_helpers.py
wefact_cli/utils/env_handler.py
wefact_cli/utils/formatters.py
wefact_cli/utils/validators.py
wefact_python-1.0.4.dist-info/licenses/LICENSE
wefact_python-1.0.4.dist-info/METADATA
wefact_python-1.0.4.dist-info/WHEEL
wefact_python-1.0.4.dist-info/entry_points.txt
wefact_python-1.0.4.dist-info/top_level.txt
wefact_python-1.0.4.dist-info/RECORD
