Metadata-Version: 2.4
Name: wefact-python
Version: 1.0.4
Summary: A Python wrapper for the WeFact API
Author-email: Sjoerd Zaalberg van Zelst <hello@zzinnovate.com>
License-Expression: MIT
Project-URL: Homepage, https://zzinnovate.github.io/wefact-python/
Project-URL: Repository, https://github.com/zzinnovate/wefact-python
Keywords: wefact,api,wrapper,python
Classifier: Development Status :: 5 - Production/Stable
Classifier: Intended Audience :: Developers
Classifier: Programming Language :: Python :: 3.11
Classifier: Programming Language :: Python :: 3.12
Classifier: Programming Language :: Python :: 3.13
Classifier: Programming Language :: Python :: 3.14
Requires-Python: <4.0,>=3.11
License-File: LICENSE
Requires-Dist: requests<3.0,>=2.26
Provides-Extra: cli
Requires-Dist: rich>=13.7.0; extra == "cli"
Requires-Dist: textual>=0.47.0; extra == "cli"
Requires-Dist: faker>=22.0.0; extra == "cli"
Requires-Dist: pydantic>=2.5.0; extra == "cli"
Requires-Dist: python-dotenv<2.0,>=1.0; extra == "cli"
Provides-Extra: dev
Requires-Dist: pytest<8.5.0,>=8.3.0; extra == "dev"
Requires-Dist: pytest-cov<7.0,>=5; extra == "dev"
Requires-Dist: pytest-mock<4.0,>=3.14.1; extra == "dev"
Provides-Extra: docs
Requires-Dist: mkdocs>=1.6.0; extra == "docs"
Requires-Dist: mkdocs-material>=9.5.0; extra == "docs"
Requires-Dist: mkdocstrings>=0.24.0; extra == "docs"
Requires-Dist: mkdocstrings-python>=1.10.0; extra == "docs"
Requires-Dist: mkdocs-mermaid2-plugin>=1.1.0; extra == "docs"
Requires-Dist: mkdocs-glightbox>=0.4.0; extra == "docs"
Requires-Dist: mkdocs-include-markdown-plugin>=6.0.0; extra == "docs"
Provides-Extra: all
Requires-Dist: wefact-python[cli,dev,docs]; extra == "all"
Dynamic: license-file
